agent_control_plane/__init__.py
agent_control_plane/a2a_adapter.py
agent_control_plane/adapter.py
agent_control_plane/agent_kernel.py
agent_control_plane/compliance.py
agent_control_plane/constraint_graphs.py
agent_control_plane/control_plane.py
agent_control_plane/example_executors.py
agent_control_plane/execution_engine.py
agent_control_plane/flight_recorder.py
agent_control_plane/governance_layer.py
agent_control_plane/langchain_adapter.py
agent_control_plane/mcp_adapter.py
agent_control_plane/ml_safety.py
agent_control_plane/multimodal.py
agent_control_plane/mute_agent.py
agent_control_plane/observability.py
agent_control_plane/orchestrator.py
agent_control_plane/plugin_registry.py
agent_control_plane/policy_engine.py
agent_control_plane/shadow_mode.py
agent_control_plane/supervisor_agents.py
agent_control_plane/tool_registry.py
agent_control_plane/interfaces/__init__.py
agent_control_plane/interfaces/kernel_interface.py
agent_control_plane/interfaces/plugin_interface.py
agent_control_plane/interfaces/protocol_interfaces.py
agent_control_plane-1.2.0.dist-info/licenses/LICENSE
agent_control_plane-1.2.0.dist-info/METADATA
agent_control_plane-1.2.0.dist-info/WHEEL
agent_control_plane-1.2.0.dist-info/top_level.txt
agent_control_plane-1.2.0.dist-info/RECORD
