Metadata-Version: 2.4
Name: agent-control-plane
Version: 1.2.0
Summary: Layer 3: The Framework - A governance and management layer for autonomous AI agents
Home-page: https://github.com/imran-siddique/agent-control-plane
Author: Agent Control Plane Contributors
Author-email: 
License-Expression: MIT
Project-URL: Homepage, https://github.com/imran-siddique/agent-control-plane
Project-URL: Documentation, https://github.com/imran-siddique/agent-control-plane/tree/main/docs
Project-URL: Repository, https://github.com/imran-siddique/agent-control-plane
Project-URL: Bug Tracker, https://github.com/imran-siddique/agent-control-plane/issues
Keywords: ai,agents,governance,control-plane,safety,policy,framework
Classifier: Development Status :: 3 - Alpha
Classifier: Intended Audience :: Developers
Classifier: Topic :: Software Development :: Libraries :: Python Modules
Classifier: Topic :: Scientific/Engineering :: Artificial Intelligence
Classifier: Programming Language :: Python :: 3
Classifier: Programming Language :: Python :: 3.8
Classifier: Programming Language :: Python :: 3.9
Classifier: Programming Language :: Python :: 3.10
Classifier: Programming Language :: Python :: 3.11
Classifier: Programming Language :: Python :: 3.12
Requires-Python: >=3.8
License-File: LICENSE
Provides-Extra: dev
Requires-Dist: pytest>=7.0.0; extra == "dev"
Requires-Dist: pytest-cov>=4.0.0; extra == "dev"
Requires-Dist: black>=23.0.0; extra == "dev"
Requires-Dist: flake8>=6.0.0; extra == "dev"
Requires-Dist: mypy>=1.0.0; extra == "dev"
Provides-Extra: protocols
Provides-Extra: full
Dynamic: home-page
Dynamic: license-file
Dynamic: requires-python
